{
  "data_iso": "2026-07-21",
  "gerado_em": "21/07/2026 18:42",
  "total": 185,
  "acoes": [
    {
      "ticker": "HYPE3",
      "preco": 20.24,
      "var_1d": -5.51,
      "var_20d": 0.79,
      "rsi": 42.1,
      "score": 65,
      "classificacao": "FORTE OPORTUNIDADE",
      "setor": "Saúde",
      "volume": 6116600
    },
    {
      "ticker": "TEND3",
      "preco": 29.64,
      "var_1d": -3.2,
      "var_20d": -15.31,
      "rsi": 31.0,
      "score": 60,
      "classificacao": "FORTE OPORTUNIDADE",
      "setor": "Financeiro",
      "volume": 2515700
    },
    {
      "ticker": "ROMI3",
      "preco": 5.86,
      "var_1d": -1.51,
      "var_20d": -2.33,
      "rsi": 33.3,
      "score": 60,
      "classificacao": "FORTE OPORTUNIDADE",
      "setor": "Bens de Capital",
      "volume": 291100
    },
    {
      "ticker": "POMO4",
      "preco": 5.1,
      "var_1d": -0.58,
      "var_20d": -12.22,
      "rsi": 27.4,
      "score": 55,
      "classificacao": "OBSERVAR",
      "setor": "Bens de Capital",
      "volume": 12738300
    },
    {
      "ticker": "DIRR3",
      "preco": 11.53,
      "var_1d": -2.45,
      "var_20d": -16.45,
      "rsi": 30.7,
      "score": 55,
      "classificacao": "OBSERVAR",
      "setor": "Financeiro",
      "volume": 8143500
    },
    {
      "ticker": "PLPL3",
      "preco": 7.26,
      "var_1d": -5.47,
      "var_20d": -12.0,
      "rsi": 33.5,
      "score": 55,
      "classificacao": "OBSERVAR",
      "setor": "Financeiro",
      "volume": 3485500
    },
    {
      "ticker": "EGIE3",
      "preco": 30.34,
      "var_1d": 0.23,
      "var_20d": -11.29,
      "rsi": 34.9,
      "score": 55,
      "classificacao": "OBSERVAR",
      "setor": "Energia Elétrica e Saneamento",
      "volume": 3402300
    },
    {
      "ticker": "SHUL4",
      "preco": 4.5,
      "var_1d": -1.1,
      "var_20d": -4.9,
      "rsi": 37.7,
      "score": 55,
      "classificacao": "OBSERVAR",
      "setor": "Bens de Capital",
      "volume": 932500
    },
    {
      "ticker": "ALLD3",
      "preco": 4.5,
      "var_1d": 0.0,
      "var_20d": -7.41,
      "rsi": 31.8,
      "score": 55,
      "classificacao": "OBSERVAR",
      "setor": "Tecnologia",
      "volume": 332400
    },
    {
      "ticker": "TFCO4",
      "preco": 13.8,
      "var_1d": -1.08,
      "var_20d": -7.8,
      "rsi": 33.8,
      "score": 55,
      "classificacao": "OBSERVAR",
      "setor": "Varejo",
      "volume": 324200
    },
    {
      "ticker": "CVCB3",
      "preco": 1.12,
      "var_1d": 3.7,
      "var_20d": -15.15,
      "rsi": 33.9,
      "score": 50,
      "classificacao": "OBSERVAR",
      "setor": "Serviços ao Consumidor",
      "volume": 16753200
    },
    {
      "ticker": "ANIM3",
      "preco": 2.08,
      "var_1d": -4.59,
      "var_20d": -19.38,
      "rsi": 34.1,
      "score": 50,
      "classificacao": "OBSERVAR",
      "setor": "Serviços ao Consumidor",
      "volume": 16740200
    },
    {
      "ticker": "BHIA3",
      "preco": 0.91,
      "var_1d": -9.9,
      "var_20d": -19.47,
      "rsi": 27.1,
      "score": 50,
      "classificacao": "OBSERVAR",
      "setor": "Varejo",
      "volume": 12386800
    },
    {
      "ticker": "MOVI3",
      "preco": 8.0,
      "var_1d": -7.08,
      "var_20d": -16.84,
      "rsi": 30.4,
      "score": 50,
      "classificacao": "OBSERVAR",
      "setor": "Financeiro",
      "volume": 8070300
    },
    {
      "ticker": "SBSP3",
      "preco": 28.6,
      "var_1d": -1.31,
      "var_20d": 1.56,
      "rsi": 42.9,
      "score": 50,
      "classificacao": "OBSERVAR",
      "setor": "Energia Elétrica e Saneamento",
      "volume": 7206700
    },
    {
      "ticker": "YDUQ3",
      "preco": 7.83,
      "var_1d": -4.16,
      "var_20d": -8.21,
      "rsi": 32.7,
      "score": 50,
      "classificacao": "OBSERVAR",
      "setor": "Serviços Comerciais",
      "volume": 6934200
    },
    {
      "ticker": "PGMN3",
      "preco": 3.42,
      "var_1d": 0.59,
      "var_20d": -7.07,
      "rsi": 33.7,
      "score": 50,
      "classificacao": "OBSERVAR",
      "setor": "Varejo",
      "volume": 3184500
    },
    {
      "ticker": "CAML3",
      "preco": 4.29,
      "var_1d": 1.18,
      "var_20d": -13.33,
      "rsi": 33.1,
      "score": 50,
      "classificacao": "OBSERVAR",
      "setor": "Indústria de Processo",
      "volume": 833800
    },
    {
      "ticker": "MTRE3",
      "preco": 2.91,
      "var_1d": -1.36,
      "var_20d": -11.27,
      "rsi": 27.0,
      "score": 50,
      "classificacao": "OBSERVAR",
      "setor": "Financeiro",
      "volume": 658400
    },
    {
      "ticker": "CEAB3",
      "preco": 9.31,
      "var_1d": -2.72,
      "var_20d": -5.1,
      "rsi": 33.2,
      "score": 45,
      "classificacao": "OBSERVAR",
      "setor": "Varejo",
      "volume": 8731900
    },
    {
      "ticker": "ECOR3",
      "preco": 6.8,
      "var_1d": -2.02,
      "var_20d": -2.58,
      "rsi": 38.0,
      "score": 45,
      "classificacao": "OBSERVAR",
      "setor": "Transporte e Logística",
      "volume": 5802700
    },
    {
      "ticker": "ENEV3",
      "preco": 25.42,
      "var_1d": -0.9,
      "var_20d": 0.87,
      "rsi": 45.4,
      "score": 45,
      "classificacao": "OBSERVAR",
      "setor": "Energia Elétrica e Saneamento",
      "volume": 4083900
    },
    {
      "ticker": "VIVA3",
      "preco": 21.41,
      "var_1d": -2.5,
      "var_20d": -2.15,
      "rsi": 39.5,
      "score": 45,
      "classificacao": "OBSERVAR",
      "setor": "Bens de Consumo",
      "volume": 3776100
    },
    {
      "ticker": "GGPS3",
      "preco": 11.8,
      "var_1d": -2.48,
      "var_20d": 1.9,
      "rsi": 41.5,
      "score": 45,
      "classificacao": "OBSERVAR",
      "setor": "Serviços Comerciais",
      "volume": 2965200
    },
    {
      "ticker": "LWSA3",
      "preco": 3.74,
      "var_1d": -3.86,
      "var_20d": -0.53,
      "rsi": 40.9,
      "score": 45,
      "classificacao": "OBSERVAR",
      "setor": "Tecnologia",
      "volume": 2454000
    },
    {
      "ticker": "POMO3",
      "preco": 4.68,
      "var_1d": -1.89,
      "var_20d": -15.68,
      "rsi": 24.5,
      "score": 45,
      "classificacao": "OBSERVAR",
      "setor": "Bens de Capital",
      "volume": 1637400
    },
    {
      "ticker": "LOGG3",
      "preco": 25.89,
      "var_1d": -1.52,
      "var_20d": -4.89,
      "rsi": 42.0,
      "score": 45,
      "classificacao": "OBSERVAR",
      "setor": "Serviços Industriais",
      "volume": 400700
    },
    {
      "ticker": "LEVE3",
      "preco": 31.45,
      "var_1d": 0.16,
      "var_20d": -3.82,
      "rsi": 36.5,
      "score": 45,
      "classificacao": "OBSERVAR",
      "setor": "Bens de Capital",
      "volume": 325600
    },
    {
      "ticker": "COGN3",
      "preco": 2.14,
      "var_1d": -1.83,
      "var_20d": -6.55,
      "rsi": 36.2,
      "score": 40,
      "classificacao": "OBSERVAR",
      "setor": "Serviços Comerciais",
      "volume": 19271600
    },
    {
      "ticker": "ONCO3",
      "preco": 0.7,
      "var_1d": 2.94,
      "var_20d": -48.15,
      "rsi": 34.6,
      "score": 40,
      "classificacao": "OBSERVAR",
      "setor": "Saúde",
      "volume": 13961000
    },
    {
      "ticker": "RDOR3",
      "preco": 33.92,
      "var_1d": -4.32,
      "var_20d": -0.7,
      "rsi": 41.7,
      "score": 40,
      "classificacao": "OBSERVAR",
      "setor": "Saúde",
      "volume": 10536300
    },
    {
      "ticker": "MRVE3",
      "preco": 4.51,
      "var_1d": -1.74,
      "var_20d": -7.96,
      "rsi": 31.4,
      "score": 40,
      "classificacao": "OBSERVAR",
      "setor": "Bens de Consumo",
      "volume": 9480200
    },
    {
      "ticker": "LREN3",
      "preco": 13.27,
      "var_1d": -0.3,
      "var_20d": -7.27,
      "rsi": 36.8,
      "score": 40,
      "classificacao": "OBSERVAR",
      "setor": "Varejo",
      "volume": 8624800
    },
    {
      "ticker": "BRKM5",
      "preco": 5.71,
      "var_1d": -3.87,
      "var_20d": -24.87,
      "rsi": 31.2,
      "score": 40,
      "classificacao": "OBSERVAR",
      "setor": "Indústria de Processo",
      "volume": 7116600
    },
    {
      "ticker": "SANB11",
      "preco": 27.21,
      "var_1d": 0.74,
      "var_20d": 1.72,
      "rsi": 53.6,
      "score": 40,
      "classificacao": "OBSERVAR",
      "setor": "Financeiro",
      "volume": 7011800
    },
    {
      "ticker": "GFSA3",
      "preco": 0.36,
      "var_1d": 0.0,
      "var_20d": -72.93,
      "rsi": 17.8,
      "score": 40,
      "classificacao": "OBSERVAR",
      "setor": "Financeiro",
      "volume": 5682500
    },
    {
      "ticker": "RAIZ4",
      "preco": 0.27,
      "var_1d": 0.0,
      "var_20d": -35.71,
      "rsi": 22.9,
      "score": 40,
      "classificacao": "OBSERVAR",
      "setor": "Varejo",
      "volume": 5193600
    },
    {
      "ticker": "SBFG3",
      "preco": 9.45,
      "var_1d": -2.68,
      "var_20d": -7.35,
      "rsi": 37.6,
      "score": 40,
      "classificacao": "OBSERVAR",
      "setor": "Varejo",
      "volume": 2000500
    },
    {
      "ticker": "EZTC3",
      "preco": 11.59,
      "var_1d": -1.78,
      "var_20d": -11.66,
      "rsi": 32.2,
      "score": 40,
      "classificacao": "OBSERVAR",
      "setor": "Financeiro",
      "volume": 1143400
    },
    {
      "ticker": "VTRU3",
      "preco": 12.0,
      "var_1d": -1.4,
      "var_20d": -10.25,
      "rsi": 31.4,
      "score": 40,
      "classificacao": "OBSERVAR",
      "setor": "Serviços Comerciais",
      "volume": 514000
    },
    {
      "ticker": "MELK3",
      "preco": 2.93,
      "var_1d": -2.01,
      "var_20d": -6.69,
      "rsi": 32.4,
      "score": 40,
      "classificacao": "OBSERVAR",
      "setor": "Serviços Industriais",
      "volume": 492200
    },
    {
      "ticker": "WEGE3",
      "preco": 42.47,
      "var_1d": -1.53,
      "var_20d": -7.09,
      "rsi": 34.2,
      "score": 35,
      "classificacao": "NEUTRO",
      "setor": "Bens de Capital",
      "volume": 8949800
    },
    {
      "ticker": "CYRE3",
      "preco": 21.18,
      "var_1d": 0.24,
      "var_20d": -1.94,
      "rsi": 41.9,
      "score": 35,
      "classificacao": "NEUTRO",
      "setor": "Financeiro",
      "volume": 5525900
    },
    {
      "ticker": "AZEV4",
      "preco": 1.2,
      "var_1d": 0.0,
      "var_20d": -33.33,
      "rsi": 31.7,
      "score": 35,
      "classificacao": "NEUTRO",
      "setor": "Serviços Industriais",
      "volume": 3330900
    },
    {
      "ticker": "CURY3",
      "preco": 29.95,
      "var_1d": -0.79,
      "var_20d": -12.76,
      "rsi": 36.9,
      "score": 35,
      "classificacao": "NEUTRO",
      "setor": "Financeiro",
      "volume": 2766900
    },
    {
      "ticker": "MULT3",
      "preco": 28.35,
      "var_1d": 0.11,
      "var_20d": -0.42,
      "rsi": 43.0,
      "score": 35,
      "classificacao": "NEUTRO",
      "setor": "Financeiro",
      "volume": 2025600
    },
    {
      "ticker": "IGTI11",
      "preco": 24.59,
      "var_1d": -1.05,
      "var_20d": 2.34,
      "rsi": 44.0,
      "score": 35,
      "classificacao": "NEUTRO",
      "setor": "Financeiro",
      "volume": 1696500
    },
    {
      "ticker": "VVEO3",
      "preco": 0.61,
      "var_1d": 7.02,
      "var_20d": -50.0,
      "rsi": 32.6,
      "score": 35,
      "classificacao": "NEUTRO",
      "setor": "Distribuição",
      "volume": 1607300
    },
    {
      "ticker": "ORVR3",
      "preco": 70.61,
      "var_1d": -3.31,
      "var_20d": -6.54,
      "rsi": 31.7,
      "score": 35,
      "classificacao": "NEUTRO",
      "setor": "Energia Elétrica e Saneamento",
      "volume": 1382100
    },
    {
      "ticker": "RIAA3",
      "preco": 7.8,
      "var_1d": -1.64,
      "var_20d": -10.18,
      "rsi": 33.9,
      "score": 35,
      "classificacao": "NEUTRO",
      "setor": "Distribuição",
      "volume": 879700
    },
    {
      "ticker": "SOJA3",
      "preco": 5.8,
      "var_1d": -2.68,
      "var_20d": -2.85,
      "rsi": 40.2,
      "score": 35,
      "classificacao": "NEUTRO",
      "setor": "Indústria de Processo",
      "volume": 866300
    },
    {
      "ticker": "IRBR3",
      "preco": 55.8,
      "var_1d": -1.76,
      "var_20d": 3.46,
      "rsi": 56.1,
      "score": 35,
      "classificacao": "NEUTRO",
      "setor": "Financeiro",
      "volume": 760700
    },
    {
      "ticker": "LAVV3",
      "preco": 10.15,
      "var_1d": -5.32,
      "var_20d": -7.31,
      "rsi": 36.5,
      "score": 35,
      "classificacao": "NEUTRO",
      "setor": "Financeiro",
      "volume": 688300
    },
    {
      "ticker": "FIQE3",
      "preco": 5.6,
      "var_1d": 0.0,
      "var_20d": -3.78,
      "rsi": 37.5,
      "score": 35,
      "classificacao": "NEUTRO",
      "setor": "Telecom",
      "volume": 580400
    },
    {
      "ticker": "ABCB4",
      "preco": 23.54,
      "var_1d": -0.04,
      "var_20d": 2.83,
      "rsi": 47.0,
      "score": 35,
      "classificacao": "NEUTRO",
      "setor": "Financeiro",
      "volume": 523900
    },
    {
      "ticker": "ITSA4",
      "preco": 13.62,
      "var_1d": -0.07,
      "var_20d": 4.53,
      "rsi": 54.4,
      "score": 30,
      "classificacao": "NEUTRO",
      "setor": "Financeiro",
      "volume": 17008500
    },
    {
      "ticker": "VALE3",
      "preco": 72.24,
      "var_1d": 0.43,
      "var_20d": -8.99,
      "rsi": 34.3,
      "score": 30,
      "classificacao": "NEUTRO",
      "setor": "Mineração",
      "volume": 12581400
    },
    {
      "ticker": "ITUB4",
      "preco": 42.53,
      "var_1d": 0.54,
      "var_20d": 3.65,
      "rsi": 54.0,
      "score": 30,
      "classificacao": "NEUTRO",
      "setor": "Financeiro",
      "volume": 9834900
    },
    {
      "ticker": "RENT3",
      "preco": 36.55,
      "var_1d": -2.51,
      "var_20d": -11.42,
      "rsi": 31.6,
      "score": 30,
      "classificacao": "NEUTRO",
      "setor": "Financeiro",
      "volume": 7513800
    },
    {
      "ticker": "RAIL3",
      "preco": 13.24,
      "var_1d": -2.43,
      "var_20d": 2.64,
      "rsi": 42.4,
      "score": 30,
      "classificacao": "NEUTRO",
      "setor": "Transporte e Logística",
      "volume": 7426700
    },
    {
      "ticker": "BBSE3",
      "preco": 41.55,
      "var_1d": 1.22,
      "var_20d": 8.57,
      "rsi": 76.6,
      "score": 30,
      "classificacao": "NEUTRO",
      "setor": "Financeiro",
      "volume": 5907400
    },
    {
      "ticker": "SAUD3",
      "preco": 14.77,
      "var_1d": -2.12,
      "var_20d": 7.54,
      "rsi": 54.1,
      "score": 30,
      "classificacao": "NEUTRO",
      "setor": "Saúde",
      "volume": 2828200
    },
    {
      "ticker": "SIMH3",
      "preco": 7.25,
      "var_1d": -3.97,
      "var_20d": -6.69,
      "rsi": 36.0,
      "score": 30,
      "classificacao": "NEUTRO",
      "setor": "Transporte e Logística",
      "volume": 2395700
    },
    {
      "ticker": "AXIA7",
      "preco": 49.55,
      "var_1d": 0.51,
      "var_20d": -6.28,
      "rsi": 41.2,
      "score": 30,
      "classificacao": "NEUTRO",
      "setor": "Energia Elétrica e Saneamento",
      "volume": 2147200
    },
    {
      "ticker": "BRAP4",
      "preco": 20.8,
      "var_1d": -0.05,
      "var_20d": -8.05,
      "rsi": 36.0,
      "score": 30,
      "classificacao": "NEUTRO",
      "setor": "Financeiro",
      "volume": 1787900
    },
    {
      "ticker": "ITUB3",
      "preco": 45.12,
      "var_1d": 0.18,
      "var_20d": 4.49,
      "rsi": 59.6,
      "score": 30,
      "classificacao": "NEUTRO",
      "setor": "Financeiro",
      "volume": 1702500
    },
    {
      "ticker": "PSSA3",
      "preco": 53.48,
      "var_1d": -1.33,
      "var_20d": 2.47,
      "rsi": 53.1,
      "score": 30,
      "classificacao": "NEUTRO",
      "setor": "Financeiro",
      "volume": 1382400
    },
    {
      "ticker": "PASS3",
      "preco": 24.44,
      "var_1d": -0.65,
      "var_20d": -2.63,
      "rsi": 42.5,
      "score": 30,
      "classificacao": "NEUTRO",
      "setor": "Energia Elétrica e Saneamento",
      "volume": 1329000
    },
    {
      "ticker": "DXCO3",
      "preco": 4.95,
      "var_1d": -1.0,
      "var_20d": 2.48,
      "rsi": 49.7,
      "score": 30,
      "classificacao": "NEUTRO",
      "setor": "Bens de Capital",
      "volume": 1168000
    },
    {
      "ticker": "CPFE3",
      "preco": 46.4,
      "var_1d": 0.17,
      "var_20d": 5.17,
      "rsi": 54.7,
      "score": 30,
      "classificacao": "NEUTRO",
      "setor": "Energia Elétrica e Saneamento",
      "volume": 950300
    },
    {
      "ticker": "LJQQ3",
      "preco": 1.14,
      "var_1d": 0.0,
      "var_20d": -17.39,
      "rsi": 36.7,
      "score": 30,
      "classificacao": "NEUTRO",
      "setor": "Varejo",
      "volume": 925700
    },
    {
      "ticker": "MILS3",
      "preco": 15.35,
      "var_1d": 0.33,
      "var_20d": -0.2,
      "rsi": 54.2,
      "score": 30,
      "classificacao": "NEUTRO",
      "setor": "Financeiro",
      "volume": 895600
    },
    {
      "ticker": "SEER3",
      "preco": 11.65,
      "var_1d": 0.6,
      "var_20d": 6.01,
      "rsi": 49.6,
      "score": 30,
      "classificacao": "NEUTRO",
      "setor": "Serviços ao Consumidor",
      "volume": 785100
    },
    {
      "ticker": "EVEN3",
      "preco": 5.0,
      "var_1d": 1.42,
      "var_20d": -10.23,
      "rsi": 36.9,
      "score": 30,
      "classificacao": "NEUTRO",
      "setor": "Financeiro",
      "volume": 781000
    },
    {
      "ticker": "RANI3",
      "preco": 7.89,
      "var_1d": -1.25,
      "var_20d": 3.41,
      "rsi": 47.6,
      "score": 30,
      "classificacao": "NEUTRO",
      "setor": "Indústria de Processo",
      "volume": 533100
    },
    {
      "ticker": "WIZC3",
      "preco": 8.2,
      "var_1d": -1.56,
      "var_20d": 5.94,
      "rsi": 51.5,
      "score": 30,
      "classificacao": "NEUTRO",
      "setor": "Financeiro",
      "volume": 203300
    },
    {
      "ticker": "BBDC4",
      "preco": 18.55,
      "var_1d": 0.76,
      "var_20d": 6.1,
      "rsi": 61.6,
      "score": 25,
      "classificacao": "NEUTRO",
      "setor": "Financeiro",
      "volume": 19403200
    },
    {
      "ticker": "MOTV3",
      "preco": 14.46,
      "var_1d": -0.69,
      "var_20d": 1.76,
      "rsi": 46.5,
      "score": 25,
      "classificacao": "NEUTRO",
      "setor": "Transporte e Logística",
      "volume": 4976100
    },
    {
      "ticker": "BBDC3",
      "preco": 16.15,
      "var_1d": 0.62,
      "var_20d": 6.15,
      "rsi": 61.8,
      "score": 25,
      "classificacao": "NEUTRO",
      "setor": "Financeiro",
      "volume": 3022700
    },
    {
      "ticker": "ISAE4",
      "preco": 28.43,
      "var_1d": 1.14,
      "var_20d": 2.08,
      "rsi": 51.3,
      "score": 25,
      "classificacao": "NEUTRO",
      "setor": "Energia Elétrica e Saneamento",
      "volume": 2701600
    },
    {
      "ticker": "QUAL3",
      "preco": 1.5,
      "var_1d": 0.0,
      "var_20d": -21.48,
      "rsi": 35.5,
      "score": 25,
      "classificacao": "NEUTRO",
      "setor": "Saúde",
      "volume": 2510600
    },
    {
      "ticker": "MDNE3",
      "preco": 24.9,
      "var_1d": -0.4,
      "var_20d": -9.45,
      "rsi": 37.2,
      "score": 25,
      "classificacao": "NEUTRO",
      "setor": "Financeiro",
      "volume": 1485500
    },
    {
      "ticker": "CASH3",
      "preco": 4.35,
      "var_1d": -4.19,
      "var_20d": 4.57,
      "rsi": 49.9,
      "score": 25,
      "classificacao": "NEUTRO",
      "setor": "Serviços Comerciais",
      "volume": 1347000
    },
    {
      "ticker": "MDIA3",
      "preco": 17.52,
      "var_1d": -0.17,
      "var_20d": 0.81,
      "rsi": 39.9,
      "score": 25,
      "classificacao": "NEUTRO",
      "setor": "Consumo Básico",
      "volume": 1098700
    },
    {
      "ticker": "SAPR11",
      "preco": 36.16,
      "var_1d": -1.18,
      "var_20d": -6.85,
      "rsi": 40.7,
      "score": 25,
      "classificacao": "NEUTRO",
      "setor": "Energia Elétrica e Saneamento",
      "volume": 1057900
    },
    {
      "ticker": "DESK3",
      "preco": 18.05,
      "var_1d": 0.89,
      "var_20d": 3.14,
      "rsi": 61.5,
      "score": 25,
      "classificacao": "NEUTRO",
      "setor": "Telecom",
      "volume": 1034000
    },
    {
      "ticker": "MLAS3",
      "preco": 1.72,
      "var_1d": 0.58,
      "var_20d": 2.38,
      "rsi": 55.7,
      "score": 25,
      "classificacao": "NEUTRO",
      "setor": "Tecnologia",
      "volume": 825800
    },
    {
      "ticker": "ALUP11",
      "preco": 33.45,
      "var_1d": 0.36,
      "var_20d": 3.69,
      "rsi": 55.2,
      "score": 25,
      "classificacao": "NEUTRO",
      "setor": "Energia Elétrica e Saneamento",
      "volume": 561000
    },
    {
      "ticker": "TTEN3",
      "preco": 15.06,
      "var_1d": -1.57,
      "var_20d": -0.86,
      "rsi": 48.6,
      "score": 25,
      "classificacao": "NEUTRO",
      "setor": "Serviços Comerciais",
      "volume": 555100
    },
    {
      "ticker": "FESA4",
      "preco": 5.95,
      "var_1d": 0.0,
      "var_20d": -1.65,
      "rsi": 45.9,
      "score": 25,
      "classificacao": "NEUTRO",
      "setor": "Mineração",
      "volume": 380200
    },
    {
      "ticker": "SANB4",
      "preco": 13.91,
      "var_1d": 1.02,
      "var_20d": 0.0,
      "rsi": 50.0,
      "score": 25,
      "classificacao": "NEUTRO",
      "setor": "Financeiro",
      "volume": 263500
    },
    {
      "ticker": "TGMA3",
      "preco": 30.74,
      "var_1d": -1.13,
      "var_20d": 1.29,
      "rsi": 51.3,
      "score": 25,
      "classificacao": "NEUTRO",
      "setor": "Transporte e Logística",
      "volume": 207800
    },
    {
      "ticker": "CMIN3",
      "preco": 5.58,
      "var_1d": 3.53,
      "var_20d": 30.37,
      "rsi": 71.2,
      "score": 20,
      "classificacao": "NEUTRO",
      "setor": "Mineração",
      "volume": 12317400
    },
    {
      "ticker": "AXIA3",
      "preco": 50.46,
      "var_1d": 0.2,
      "var_20d": -6.93,
      "rsi": 39.4,
      "score": 20,
      "classificacao": "NEUTRO",
      "setor": "Energia Elétrica e Saneamento",
      "volume": 10124700
    },
    {
      "ticker": "ASAI3",
      "preco": 8.25,
      "var_1d": 1.35,
      "var_20d": 3.9,
      "rsi": 43.3,
      "score": 20,
      "classificacao": "NEUTRO",
      "setor": "Varejo",
      "volume": 6066400
    },
    {
      "ticker": "UGPA3",
      "preco": 31.82,
      "var_1d": 0.38,
      "var_20d": 24.83,
      "rsi": 74.0,
      "score": 20,
      "classificacao": "NEUTRO",
      "setor": "Varejo",
      "volume": 5363000
    },
    {
      "ticker": "BEEF3",
      "preco": 3.52,
      "var_1d": -1.68,
      "var_20d": -1.4,
      "rsi": 41.8,
      "score": 20,
      "classificacao": "NEUTRO",
      "setor": "Distribuição",
      "volume": 4120800
    },
    {
      "ticker": "AURE3",
      "preco": 11.21,
      "var_1d": -0.88,
      "var_20d": -1.32,
      "rsi": 39.9,
      "score": 20,
      "classificacao": "NEUTRO",
      "setor": "Energia Elétrica e Saneamento",
      "volume": 2651800
    },
    {
      "ticker": "CSMG3",
      "preco": 63.16,
      "var_1d": -1.07,
      "var_20d": 8.01,
      "rsi": 56.2,
      "score": 20,
      "classificacao": "NEUTRO",
      "setor": "Energia Elétrica e Saneamento",
      "volume": 2635300
    },
    {
      "ticker": "INTB3",
      "preco": 13.24,
      "var_1d": 0.46,
      "var_20d": -1.85,
      "rsi": 48.7,
      "score": 20,
      "classificacao": "NEUTRO",
      "setor": "Tecnologia",
      "volume": 2112100
    },
    {
      "ticker": "RAPT4",
      "preco": 4.67,
      "var_1d": -3.51,
      "var_20d": 5.9,
      "rsi": 47.5,
      "score": 20,
      "classificacao": "NEUTRO",
      "setor": "Bens de Capital",
      "volume": 1936200
    },
    {
      "ticker": "AMBP3",
      "preco": 0.15,
      "var_1d": 0.0,
      "var_20d": -16.67,
      "rsi": 39.7,
      "score": 20,
      "classificacao": "NEUTRO",
      "setor": "Serviços Comerciais",
      "volume": 1631100
    },
    {
      "ticker": "TAEE11",
      "preco": 41.13,
      "var_1d": -0.05,
      "var_20d": 3.37,
      "rsi": 57.2,
      "score": 20,
      "classificacao": "NEUTRO",
      "setor": "Serviços Industriais",
      "volume": 1500400
    },
    {
      "ticker": "GRND3",
      "preco": 3.78,
      "var_1d": -0.79,
      "var_20d": -2.07,
      "rsi": 42.8,
      "score": 20,
      "classificacao": "NEUTRO",
      "setor": "Consumo Básico",
      "volume": 1343100
    },
    {
      "ticker": "PINE4",
      "preco": 11.61,
      "var_1d": -1.11,
      "var_20d": -9.32,
      "rsi": 42.4,
      "score": 20,
      "classificacao": "NEUTRO",
      "setor": "Financeiro",
      "volume": 883500
    },
    {
      "ticker": "SAPR4",
      "preco": 7.04,
      "var_1d": -0.42,
      "var_20d": -5.5,
      "rsi": 40.5,
      "score": 20,
      "classificacao": "NEUTRO",
      "setor": "Energia Elétrica e Saneamento",
      "volume": 763800
    },
    {
      "ticker": "BMGB4",
      "preco": 5.23,
      "var_1d": -0.19,
      "var_20d": -2.43,
      "rsi": 48.3,
      "score": 20,
      "classificacao": "NEUTRO",
      "setor": "Financeiro",
      "volume": 690000
    },
    {
      "ticker": "KEPL3",
      "preco": 6.36,
      "var_1d": 0.47,
      "var_20d": -3.64,
      "rsi": 40.2,
      "score": 20,
      "classificacao": "NEUTRO",
      "setor": "Bens de Capital",
      "volume": 532900
    },
    {
      "ticker": "VLID3",
      "preco": 17.68,
      "var_1d": -1.45,
      "var_20d": 2.02,
      "rsi": 50.3,
      "score": 20,
      "classificacao": "NEUTRO",
      "setor": "Serviços Comerciais",
      "volume": 245100
    },
    {
      "ticker": "PETR4",
      "preco": 41.66,
      "var_1d": 1.24,
      "var_20d": 5.92,
      "rsi": 62.5,
      "score": 15,
      "classificacao": "EVITAR",
      "setor": "Petróleo e Gás",
      "volume": 38631400
    },
    {
      "ticker": "VBBR3",
      "preco": 33.95,
      "var_1d": -0.47,
      "var_20d": 15.52,
      "rsi": 67.9,
      "score": 15,
      "classificacao": "EVITAR",
      "setor": "Varejo",
      "volume": 10385900
    },
    {
      "ticker": "CMIG4",
      "preco": 11.02,
      "var_1d": 0.0,
      "var_20d": 2.33,
      "rsi": 51.3,
      "score": 15,
      "classificacao": "EVITAR",
      "setor": "Energia Elétrica e Saneamento",
      "volume": 8895800
    },
    {
      "ticker": "EQTL3",
      "preco": 38.83,
      "var_1d": -1.17,
      "var_20d": 1.65,
      "rsi": 46.1,
      "score": 15,
      "classificacao": "EVITAR",
      "setor": "Energia Elétrica e Saneamento",
      "volume": 7346900
    },
    {
      "ticker": "PETR3",
      "preco": 46.78,
      "var_1d": 1.43,
      "var_20d": 6.37,
      "rsi": 62.4,
      "score": 15,
      "classificacao": "EVITAR",
      "setor": "Petróleo e Gás",
      "volume": 6728700
    },
    {
      "ticker": "SMFT3",
      "preco": 19.97,
      "var_1d": -0.75,
      "var_20d": 5.94,
      "rsi": 51.0,
      "score": 15,
      "classificacao": "EVITAR",
      "setor": "Serviços ao Consumidor",
      "volume": 5911500
    },
    {
      "ticker": "BPAC11",
      "preco": 55.37,
      "var_1d": -0.84,
      "var_20d": 4.87,
      "rsi": 51.1,
      "score": 15,
      "classificacao": "EVITAR",
      "setor": "Financeiro",
      "volume": 5416600
    },
    {
      "ticker": "PCAR3",
      "preco": 2.73,
      "var_1d": 5.0,
      "var_20d": 31.25,
      "rsi": 64.6,
      "score": 15,
      "classificacao": "EVITAR",
      "setor": "Varejo",
      "volume": 4196500
    },
    {
      "ticker": "GGBR4",
      "preco": 23.49,
      "var_1d": -0.55,
      "var_20d": 8.25,
      "rsi": 58.5,
      "score": 15,
      "classificacao": "EVITAR",
      "setor": "Mineração",
      "volume": 4029600
    },
    {
      "ticker": "EMBJ3",
      "preco": 82.65,
      "var_1d": -0.77,
      "var_20d": 5.26,
      "rsi": 55.1,
      "score": 15,
      "classificacao": "EVITAR",
      "setor": "Tecnologia",
      "volume": 3367100
    },
    {
      "ticker": "JHSF3",
      "preco": 11.03,
      "var_1d": 2.6,
      "var_20d": 3.25,
      "rsi": 52.9,
      "score": 15,
      "classificacao": "EVITAR",
      "setor": "Financeiro",
      "volume": 3364000
    },
    {
      "ticker": "TIMS3",
      "preco": 22.67,
      "var_1d": 0.31,
      "var_20d": 1.66,
      "rsi": 52.5,
      "score": 15,
      "classificacao": "EVITAR",
      "setor": "Telecom",
      "volume": 3157800
    },
    {
      "ticker": "GOAU4",
      "preco": 10.23,
      "var_1d": -0.68,
      "var_20d": 7.12,
      "rsi": 56.9,
      "score": 15,
      "classificacao": "EVITAR",
      "setor": "Mineração",
      "volume": 2848400
    },
    {
      "ticker": "SUZB3",
      "preco": 41.63,
      "var_1d": -0.62,
      "var_20d": -0.76,
      "rsi": 50.9,
      "score": 15,
      "classificacao": "EVITAR",
      "setor": "Indústria de Processo",
      "volume": 2360900
    },
    {
      "ticker": "AZEV3",
      "preco": 1.9,
      "var_1d": 15.15,
      "var_20d": -32.14,
      "rsi": 44.9,
      "score": 15,
      "classificacao": "EVITAR",
      "setor": "Serviços Industriais",
      "volume": 2164500
    },
    {
      "ticker": "LIGT3",
      "preco": 3.07,
      "var_1d": -6.12,
      "var_20d": 3.37,
      "rsi": 48.0,
      "score": 15,
      "classificacao": "EVITAR",
      "setor": "Energia Elétrica e Saneamento",
      "volume": 2007600
    },
    {
      "ticker": "FLRY3",
      "preco": 16.55,
      "var_1d": -0.06,
      "var_20d": 9.82,
      "rsi": 64.6,
      "score": 15,
      "classificacao": "EVITAR",
      "setor": "Saúde",
      "volume": 1793100
    },
    {
      "ticker": "ENJU3",
      "preco": 0.86,
      "var_1d": -7.53,
      "var_20d": 4.59,
      "rsi": 52.4,
      "score": 15,
      "classificacao": "EVITAR",
      "setor": "Varejo",
      "volume": 1453500
    },
    {
      "ticker": "BRSR6",
      "preco": 14.25,
      "var_1d": 1.64,
      "var_20d": 5.17,
      "rsi": 52.0,
      "score": 15,
      "classificacao": "EVITAR",
      "setor": "Financeiro",
      "volume": 957500
    },
    {
      "ticker": "TUPY3",
      "preco": 15.39,
      "var_1d": -3.93,
      "var_20d": 6.73,
      "rsi": 54.6,
      "score": 15,
      "classificacao": "EVITAR",
      "setor": "Bens de Capital",
      "volume": 871800
    },
    {
      "ticker": "USIM3",
      "preco": 7.54,
      "var_1d": 2.86,
      "var_20d": -4.31,
      "rsi": 42.5,
      "score": 15,
      "classificacao": "EVITAR",
      "setor": "Mineração",
      "volume": 643900
    },
    {
      "ticker": "SHOW3",
      "preco": 6.02,
      "var_1d": 1.01,
      "var_20d": 3.08,
      "rsi": 60.5,
      "score": 15,
      "classificacao": "EVITAR",
      "setor": "Serviços ao Consumidor",
      "volume": 536900
    },
    {
      "ticker": "OPCT3",
      "preco": 10.96,
      "var_1d": -1.26,
      "var_20d": 6.82,
      "rsi": 55.3,
      "score": 15,
      "classificacao": "EVITAR",
      "setor": "Serviços Comerciais",
      "volume": 517900
    },
    {
      "ticker": "INEP3",
      "preco": 1.65,
      "var_1d": 5.1,
      "var_20d": -14.51,
      "rsi": 37.1,
      "score": 15,
      "classificacao": "EVITAR",
      "setor": "Bens de Capital",
      "volume": 489300
    },
    {
      "ticker": "BBAS3",
      "preco": 20.88,
      "var_1d": 3.52,
      "var_20d": 5.14,
      "rsi": 59.2,
      "score": 10,
      "classificacao": "EVITAR",
      "setor": "Financeiro",
      "volume": 25335900
    },
    {
      "ticker": "CSAN3",
      "preco": 3.78,
      "var_1d": -1.05,
      "var_20d": 0.8,
      "rsi": 47.0,
      "score": 10,
      "classificacao": "EVITAR",
      "setor": "Energia Elétrica e Saneamento",
      "volume": 13007000
    },
    {
      "ticker": "CPLE3",
      "preco": 14.51,
      "var_1d": -2.68,
      "var_20d": -3.2,
      "rsi": 42.2,
      "score": 10,
      "classificacao": "EVITAR",
      "setor": "Energia Elétrica e Saneamento",
      "volume": 9994100
    },
    {
      "ticker": "MBRF3",
      "preco": 15.11,
      "var_1d": 4.06,
      "var_20d": -10.06,
      "rsi": 41.7,
      "score": 10,
      "classificacao": "EVITAR",
      "setor": "Consumo Básico",
      "volume": 9246900
    },
    {
      "ticker": "VAMO3",
      "preco": 3.09,
      "var_1d": 0.0,
      "var_20d": 9.96,
      "rsi": 55.1,
      "score": 10,
      "classificacao": "EVITAR",
      "setor": "Financeiro",
      "volume": 6882400
    },
    {
      "ticker": "RCSL4",
      "preco": 0.51,
      "var_1d": 0.0,
      "var_20d": -8.93,
      "rsi": 56.5,
      "score": 10,
      "classificacao": "EVITAR",
      "setor": "Bens de Capital",
      "volume": 4998200
    },
    {
      "ticker": "BRAV3",
      "preco": 20.14,
      "var_1d": 0.8,
      "var_20d": 6.17,
      "rsi": 59.7,
      "score": 10,
      "classificacao": "EVITAR",
      "setor": "Petróleo e Gás",
      "volume": 4766700
    },
    {
      "ticker": "TOTS3",
      "preco": 28.57,
      "var_1d": -0.9,
      "var_20d": 3.7,
      "rsi": 44.6,
      "score": 10,
      "classificacao": "EVITAR",
      "setor": "Tecnologia",
      "volume": 3840500
    },
    {
      "ticker": "ALOS3",
      "preco": 27.1,
      "var_1d": -0.73,
      "var_20d": 0.59,
      "rsi": 43.4,
      "score": 10,
      "classificacao": "EVITAR",
      "setor": "Financeiro",
      "volume": 3393000
    },
    {
      "ticker": "KLBN11",
      "preco": 17.59,
      "var_1d": 0.63,
      "var_20d": 4.64,
      "rsi": 61.2,
      "score": 10,
      "classificacao": "EVITAR",
      "setor": "Mineração",
      "volume": 3098500
    },
    {
      "ticker": "GMAT3",
      "preco": 3.83,
      "var_1d": -0.52,
      "var_20d": -0.26,
      "rsi": 46.5,
      "score": 10,
      "classificacao": "EVITAR",
      "setor": "Varejo",
      "volume": 2763900
    },
    {
      "ticker": "CBAV3",
      "preco": 10.84,
      "var_1d": 0.28,
      "var_20d": 1.12,
      "rsi": 59.7,
      "score": 10,
      "classificacao": "EVITAR",
      "setor": "Mineração",
      "volume": 2551600
    },
    {
      "ticker": "CXSE3",
      "preco": 22.33,
      "var_1d": 0.22,
      "var_20d": 14.93,
      "rsi": 79.9,
      "score": 10,
      "classificacao": "EVITAR",
      "setor": "Financeiro",
      "volume": 2500000
    },
    {
      "ticker": "VULC3",
      "preco": 14.25,
      "var_1d": 0.21,
      "var_20d": -1.86,
      "rsi": 46.4,
      "score": 10,
      "classificacao": "EVITAR",
      "setor": "Consumo Básico",
      "volume": 1056600
    },
    {
      "ticker": "ALPA4",
      "preco": 11.83,
      "var_1d": -0.42,
      "var_20d": -10.38,
      "rsi": 43.5,
      "score": 10,
      "classificacao": "EVITAR",
      "setor": "Consumo Básico",
      "volume": 1010300
    },
    {
      "ticker": "JALL3",
      "preco": 2.02,
      "var_1d": 0.5,
      "var_20d": -8.6,
      "rsi": 36.2,
      "score": 10,
      "classificacao": "EVITAR",
      "setor": "Indústria de Processo",
      "volume": 870300
    },
    {
      "ticker": "OIBR3",
      "preco": 0.12,
      "var_1d": 0.0,
      "var_20d": 20.0,
      "rsi": 50.0,
      "score": 10,
      "classificacao": "EVITAR",
      "setor": "Telecom",
      "volume": 786000
    },
    {
      "ticker": "ARML3",
      "preco": 3.09,
      "var_1d": -3.13,
      "var_20d": 7.29,
      "rsi": 45.7,
      "score": 10,
      "classificacao": "EVITAR",
      "setor": "Financeiro",
      "volume": 710600
    },
    {
      "ticker": "PRNR3",
      "preco": 18.25,
      "var_1d": -1.19,
      "var_20d": 3.52,
      "rsi": 48.0,
      "score": 10,
      "classificacao": "EVITAR",
      "setor": "Serviços Industriais",
      "volume": 466100
    },
    {
      "ticker": "BRST3",
      "preco": 2.8,
      "var_1d": 1.08,
      "var_20d": 5.26,
      "rsi": 51.8,
      "score": 10,
      "classificacao": "EVITAR",
      "setor": "Telecom",
      "volume": 281000
    },
    {
      "ticker": "PNVL3",
      "preco": 11.26,
      "var_1d": 0.18,
      "var_20d": 3.65,
      "rsi": 53.0,
      "score": 10,
      "classificacao": "EVITAR",
      "setor": "Varejo",
      "volume": 262200
    },
    {
      "ticker": "BMOB3",
      "preco": 23.3,
      "var_1d": -0.38,
      "var_20d": 0.43,
      "rsi": 45.4,
      "score": 10,
      "classificacao": "EVITAR",
      "setor": "Tecnologia",
      "volume": 248200
    },
    {
      "ticker": "OBTC3",
      "preco": 6.42,
      "var_1d": 4.56,
      "var_20d": 4.05,
      "rsi": 58.5,
      "score": 10,
      "classificacao": "EVITAR",
      "setor": "Tecnologia",
      "volume": 247500
    },
    {
      "ticker": "SANB3",
      "preco": 13.35,
      "var_1d": 0.68,
      "var_20d": 3.81,
      "rsi": 57.6,
      "score": 10,
      "classificacao": "EVITAR",
      "setor": "Financeiro",
      "volume": 232700
    },
    {
      "ticker": "B3SA3",
      "preco": 15.17,
      "var_1d": -0.59,
      "var_20d": 4.6,
      "rsi": 50.8,
      "score": 5,
      "classificacao": "EVITAR",
      "setor": "Financeiro",
      "volume": 29244400
    },
    {
      "ticker": "RADL3",
      "preco": 18.13,
      "var_1d": -3.0,
      "var_20d": 7.37,
      "rsi": 51.9,
      "score": 5,
      "classificacao": "EVITAR",
      "setor": "Varejo",
      "volume": 13563600
    },
    {
      "ticker": "USIM5",
      "preco": 8.46,
      "var_1d": 3.68,
      "var_20d": -2.31,
      "rsi": 45.1,
      "score": 5,
      "classificacao": "EVITAR",
      "setor": "Mineração",
      "volume": 9783100
    },
    {
      "ticker": "CSNA3",
      "preco": 5.06,
      "var_1d": -0.2,
      "var_20d": -3.98,
      "rsi": 44.8,
      "score": 5,
      "classificacao": "EVITAR",
      "setor": "Mineração",
      "volume": 9070800
    },
    {
      "ticker": "KLBN4",
      "preco": 3.53,
      "var_1d": 0.86,
      "var_20d": 4.75,
      "rsi": 62.1,
      "score": 5,
      "classificacao": "EVITAR",
      "setor": "Mineração",
      "volume": 2997700
    },
    {
      "ticker": "AUAU3",
      "preco": 3.14,
      "var_1d": -0.63,
      "var_20d": -2.18,
      "rsi": 45.6,
      "score": 5,
      "classificacao": "EVITAR",
      "setor": "Indústria de Processo",
      "volume": 2828500
    },
    {
      "ticker": "VIVT3",
      "preco": 35.8,
      "var_1d": 0.36,
      "var_20d": 4.65,
      "rsi": 61.2,
      "score": 5,
      "classificacao": "EVITAR",
      "setor": "Telecom",
      "volume": 2613000
    },
    {
      "ticker": "SLCE3",
      "preco": 13.75,
      "var_1d": 1.33,
      "var_20d": 2.15,
      "rsi": 49.4,
      "score": 5,
      "classificacao": "EVITAR",
      "setor": "Indústria de Processo",
      "volume": 1787800
    },
    {
      "ticker": "AZZA3",
      "preco": 17.48,
      "var_1d": -3.8,
      "var_20d": -13.03,
      "rsi": 42.2,
      "score": 5,
      "classificacao": "EVITAR",
      "setor": "Consumo Básico",
      "volume": 1742100
    },
    {
      "ticker": "SMTO3",
      "preco": 15.58,
      "var_1d": 1.1,
      "var_20d": 6.98,
      "rsi": 48.4,
      "score": 5,
      "classificacao": "EVITAR",
      "setor": "Indústria de Processo",
      "volume": 1359700
    },
    {
      "ticker": "RECV3",
      "preco": 10.34,
      "var_1d": 1.77,
      "var_20d": 2.27,
      "rsi": 51.1,
      "score": 5,
      "classificacao": "EVITAR",
      "setor": "Petróleo e Gás",
      "volume": 1241700
    },
    {
      "ticker": "AMER3",
      "preco": 3.92,
      "var_1d": 0.77,
      "var_20d": -8.62,
      "rsi": 45.7,
      "score": 5,
      "classificacao": "EVITAR",
      "setor": "Varejo",
      "volume": 789000
    },
    {
      "ticker": "JSLG3",
      "preco": 5.69,
      "var_1d": 0.35,
      "var_20d": 4.4,
      "rsi": 49.7,
      "score": 5,
      "classificacao": "EVITAR",
      "setor": "Transporte e Logística",
      "volume": 562500
    },
    {
      "ticker": "SEQL3",
      "preco": 0.07,
      "var_1d": 0.0,
      "var_20d": 0.0,
      "rsi": 46.0,
      "score": 5,
      "classificacao": "EVITAR",
      "setor": "Transporte e Logística",
      "volume": 493500
    },
    {
      "ticker": "MATD3",
      "preco": 4.78,
      "var_1d": -0.21,
      "var_20d": 1.49,
      "rsi": 46.9,
      "score": 5,
      "classificacao": "EVITAR",
      "setor": "Saúde",
      "volume": 345800
    },
    {
      "ticker": "AZTE3",
      "preco": 1.35,
      "var_1d": 3.85,
      "var_20d": -15.62,
      "rsi": 40.9,
      "score": 5,
      "classificacao": "EVITAR",
      "setor": "Petróleo e Gás",
      "volume": 331200
    },
    {
      "ticker": "ABEV3",
      "preco": 15.8,
      "var_1d": 0.06,
      "var_20d": -3.48,
      "rsi": 45.5,
      "score": 0,
      "classificacao": "EVITAR",
      "setor": "Consumo Básico",
      "volume": 19628700
    },
    {
      "ticker": "HAPV3",
      "preco": 11.24,
      "var_1d": -2.68,
      "var_20d": 9.34,
      "rsi": 55.2,
      "score": 0,
      "classificacao": "EVITAR",
      "setor": "Saúde",
      "volume": 6142600
    },
    {
      "ticker": "NATU3",
      "preco": 8.71,
      "var_1d": 0.93,
      "var_20d": 12.82,
      "rsi": 53.1,
      "score": 0,
      "classificacao": "EVITAR",
      "setor": "Consumo Básico",
      "volume": 5492900
    },
    {
      "ticker": "PMAM3",
      "preco": 0.32,
      "var_1d": -5.88,
      "var_20d": 14.29,
      "rsi": 54.1,
      "score": 0,
      "classificacao": "EVITAR",
      "setor": "Mineração",
      "volume": 5067200
    },
    {
      "ticker": "ENGI11",
      "preco": 49.02,
      "var_1d": -0.95,
      "var_20d": 5.06,
      "rsi": 50.1,
      "score": 0,
      "classificacao": "EVITAR",
      "setor": "Energia Elétrica e Saneamento",
      "volume": 2045000
    },
    {
      "ticker": "DASA3",
      "preco": 2.86,
      "var_1d": -0.35,
      "var_20d": 3.62,
      "rsi": 56.2,
      "score": 0,
      "classificacao": "EVITAR",
      "setor": "Saúde",
      "volume": 583000
    },
    {
      "ticker": "MYPK3",
      "preco": 9.35,
      "var_1d": 0.11,
      "var_20d": 2.75,
      "rsi": 56.2,
      "score": 0,
      "classificacao": "EVITAR",
      "setor": "Bens de Capital",
      "volume": 486000
    },
    {
      "ticker": "MGLU3",
      "preco": 4.82,
      "var_1d": -0.82,
      "var_20d": 9.05,
      "rsi": 45.3,
      "score": -5,
      "classificacao": "EVITAR",
      "setor": "Varejo",
      "volume": 14370100
    },
    {
      "ticker": "KLBN3",
      "preco": 3.54,
      "var_1d": 0.57,
      "var_20d": 5.67,
      "rsi": 63.0,
      "score": -5,
      "classificacao": "EVITAR",
      "setor": "Mineração",
      "volume": 679400
    },
    {
      "ticker": "PRIO3",
      "preco": 58.18,
      "var_1d": 0.85,
      "var_20d": 3.71,
      "rsi": 55.7,
      "score": -10,
      "classificacao": "EVITAR",
      "setor": "Petróleo e Gás",
      "volume": 4489200
    },
    {
      "ticker": "HBSA3",
      "preco": 3.37,
      "var_1d": 2.12,
      "var_20d": -6.13,
      "rsi": 47.3,
      "score": -10,
      "classificacao": "EVITAR",
      "setor": "Transporte e Logística",
      "volume": 1300900
    },
    {
      "ticker": "HBOR3",
      "preco": 1.91,
      "var_1d": -5.91,
      "var_20d": -14.35,
      "rsi": 41.3,
      "score": -10,
      "classificacao": "EVITAR",
      "setor": "Bens de Consumo",
      "volume": 818400
    }
  ]
}